django_keybase_proofs-0.0.8.dist-info/METADATA
django_keybase_proofs-0.0.8.dist-info/RECORD
django_keybase_proofs-0.0.8.dist-info/WHEEL
django_keybase_proofs-0.0.8.dist-info/top_level.txt
keybase_proofs/__init__.py
keybase_proofs/models.py
keybase_proofs/urls.py
keybase_proofs/users.py
keybase_proofs/views.py
keybase_proofs/migrations/0001_initial.py
keybase_proofs/migrations/0002_keybaseproof_is_verified.py
keybase_proofs/migrations/__init__.py
keybase_proofs/templates/keybase_proofs/_base.html
keybase_proofs/templates/keybase_proofs/profile.html
keybase_proofs/templates/keybase_proofs/profile_confirm.html
keybase_proofs/tests/__init__.py
keybase_proofs/tests/views.py
test_app/__init__.py
test_app/settings.py
test_app/urls.py
test_app/views.py
test_app/wsgi.py
